GoogleImageScraper/GoogleImageScraper.py
GoogleImageScraper/__init__.py
GoogleImageScraper/errors.py
GoogleImageScraper-2.3.5.dist-info/LICENSE
GoogleImageScraper-2.3.5.dist-info/METADATA
GoogleImageScraper-2.3.5.dist-info/WHEEL
GoogleImageScraper-2.3.5.dist-info/top_level.txt
GoogleImageScraper-2.3.5.dist-info/RECORD
