Metadata-Version: 2.1
Name: GoogleImageScraper
Version: 2.3.5
Summary: This is a library for retrieving urls and downloading images from Google Images.
Home-page: https://github.com/commonkestrel/GoogleImageScraper
Author: Jibble
License: MIT
Requires-Python: >= 3.4
License-File: LICENSE
Requires-Dist: DynamicHtml
